{"kind":"identitytoolkit#DownloadAccountResponse","users":[{"localId":"d5OH5tsRIbGrsrHHUCp3NvumjzZG","createdAt":"1693560538131","lastLoginAt":"1693560538131","displayName":"Raccoon Otter","providerUserInfo":[{"providerId":"google.com","rawId":"8035418611262936951468007790717581410276","federatedId":"8035418611262936951468007790717581410276","displayName":"Raccoon Otter","email":"raccoon.otter.180@example.com","screenName":"otter_raccoon"}],"validSince":"1693566680","email":"raccoon.otter.180@example.com","emailVerified":true,"disabled":false}]}